lyzr_kit/__init__.py
lyzr_kit/main.py
lyzr_kit/py.typed
lyzr_kit/collection/agents/chat-agent.yaml
lyzr_kit/collection/agents/code-reviewer.yaml
lyzr_kit/collection/agents/content-writer.yaml
lyzr_kit/collection/agents/customer-support.yaml
lyzr_kit/collection/agents/data-analyst.yaml
lyzr_kit/collection/agents/email-composer.yaml
lyzr_kit/collection/agents/qa-agent.yaml
lyzr_kit/collection/agents/research-assistant.yaml
lyzr_kit/collection/agents/sql-expert.yaml
lyzr_kit/collection/agents/summarizer.yaml
lyzr_kit/collection/agents/task-planner.yaml
lyzr_kit/collection/agents/translator.yaml
lyzr_kit/collection/features/README.md
lyzr_kit/collection/tools/README.md
lyzr_kit/commands/__init__.py
lyzr_kit/commands/_auth_helper.py
lyzr_kit/commands/_console.py
lyzr_kit/commands/_resolver.py
lyzr_kit/commands/_websocket.py
lyzr_kit/commands/agent.py
lyzr_kit/commands/agent_chat.py
lyzr_kit/commands/agent_get.py
lyzr_kit/commands/agent_list.py
lyzr_kit/commands/agent_set.py
lyzr_kit/commands/auth.py
lyzr_kit/commands/feature.py
lyzr_kit/commands/tool.py
lyzr_kit/schemas/__init__.py
lyzr_kit/schemas/agent.py
lyzr_kit/schemas/feature.py
lyzr_kit/schemas/tool.py
lyzr_kit/storage/__init__.py
lyzr_kit/storage/manager.py
lyzr_kit/storage/project.py
lyzr_kit/storage/serialization.py
lyzr_kit/storage/validator.py
lyzr_kit/utils/__init__.py
lyzr_kit/utils/auth.py
lyzr_kit/utils/platform.py
lyzr_kit-0.2.2.dist-info/METADATA
lyzr_kit-0.2.2.dist-info/WHEEL
lyzr_kit-0.2.2.dist-info/entry_points.txt
lyzr_kit-0.2.2.dist-info/licenses/LICENSE
lyzr_kit-0.2.2.dist-info/RECORD
