Metadata-Version: 2.4
Name: lyzr-kit
Version: 0.2.2
Summary: Python SDK for managing AI agents, tools, and features via the Lyzr platform
Project-URL: Homepage, https://github.com/LyzrCore/lyzr-kit
Project-URL: Documentation, https://github.com/LyzrCore/lyzr-kit
Project-URL: Repository, https://github.com/LyzrCore/lyzr-kit
Author-email: Lyzr <support@lyzr.ai>
License-Expression: MIT
License-File: LICENSE
Keywords: agents,ai,llm,lyzr
Classifier: Development Status :: 3 - Alpha
Classifier: Intended Audience :: Developers
Classifier: License :: OSI Approved :: MIT License
Classifier: Programming Language :: Python :: 3
Classifier: Programming Language :: Python :: 3.10
Classifier: Programming Language :: Python :: 3.11
Classifier: Programming Language :: Python :: 3.12
Requires-Python: >=3.10
Requires-Dist: httpx>=0.27
Requires-Dist: prompt-toolkit>=3.0
Requires-Dist: pydantic>=2.0
Requires-Dist: python-dotenv>=1.0
Requires-Dist: pyyaml>=6.0
Requires-Dist: rich>=13.0
Requires-Dist: typer>=0.9
Requires-Dist: websockets>=12.0
Provides-Extra: dev
Requires-Dist: mypy>=1.0; extra == 'dev'
Requires-Dist: pytest-cov>=4.0; extra == 'dev'
Requires-Dist: pytest>=8.0; extra == 'dev'
Requires-Dist: ruff>=0.8; extra == 'dev'
